tsdapiclient/__init__.py
tsdapiclient/_version.py
tsdapiclient/administrator.py
tsdapiclient/authapi.py
tsdapiclient/client_config.py
tsdapiclient/configurer.py
tsdapiclient/crypto.py
tsdapiclient/exc.py
tsdapiclient/fileapi.py
tsdapiclient/guide.py
tsdapiclient/session.py
tsdapiclient/sync.py
tsdapiclient/tacl.py
tsdapiclient/tools.py
tsd_api_client-3.9.2.dist-info/METADATA
tsd_api_client-3.9.2.dist-info/WHEEL
tsd_api_client-3.9.2.dist-info/entry_points.txt
tsd_api_client-3.9.2.dist-info/licenses/LICENSE
tsd_api_client-3.9.2.dist-info/RECORD
