Metadata-Version: 2.4
Name: tsd-api-client
Version: 3.9.2
Summary: A client for the TSD REST API
License: BSD-3-Clause
License-File: LICENSE
Author: Leon du Toit
Author-email: l.c.d.toit@usit.uio.no
Maintainer: Eirik Haatveit
Maintainer-email: haatveit@uio.no
Requires-Python: >=3.8,<4.0
Classifier: License :: OSI Approved :: BSD License
Classifier: Programming Language :: Python :: 3
Classifier: Programming Language :: Python :: 3.8
Classifier: Programming Language :: Python :: 3.9
Classifier: Programming Language :: Python :: 3.10
Classifier: Programming Language :: Python :: 3.11
Classifier: Programming Language :: Python :: 3.12
Classifier: Programming Language :: Python :: 3.13
Classifier: Programming Language :: Python :: 3.14
Requires-Dist: PyYAML
Requires-Dist: click (>=8)
Requires-Dist: humanfriendly
Requires-Dist: libnacl
Requires-Dist: requests
Requires-Dist: rich
Project-URL: Repository, https://github.com/unioslo/tsd-api-client
